[
    {
        "object": {
            "id": "https://class.whalespace.io/bubblecon-guide/lecture/1019/contents/10191496",
            "objectType": "Activity",
            "definition": {
                "name": {
                    "en-US": "\uc774\uc57c\uae30 \ud480\uae30\uc758 \uae30\uc220"
                },
                "description": {
                    "en-US": "\uae00\uc4f0\uae30\uc640 \ud504\ub808\uc820\ud14c\uc774\uc158\uc744 \ud1b5\ud574 \ub9e4\ub825\uc801\uc778 \uc774\uc57c\uae30\ub97c \ub9cc\ub4ed\ub2c8\ub2e4."
                },
                "type": "http://activitystrea.ms/schema/1.0/collection",
                "extensions": {
                    "https://class.whalespace.io/classes/class/chapters/chapter/lectures/lecture/content-id": 10191496,
                    "https://class.whalespace.io/classes/class/chapters/chapter/lectures/lecture/content-order": 1,
                    "https://class.whalespace.io/classes/class/id": 123,
                    "https://class.whalespace.io/classes/class/name": "\ud589\ubcf5\ud55c \ud074\ub798\uc2a4",
                    "https://class.whalespace.io/classes/class/type": "group",
                    "https://class.whalespace.io/classes/class/chapters/chapter/id": 123,
                    "https://class.whalespace.io/classes/class/chapters/chapter/name": "\ucc55\ud130 1",
                    "https://class.whalespace.io/classes/class/chapters/chapter/lectures/lecture/id": 1019,
                    "https://class.whalespace.io/classes/class/chapters/chapter/lectures/lecture/name": "\uacbd\uc81c\ud559 \uc785\ubb38",
                    "https://class.whalespace.io/classes/class/chapters/chapter/lectures/lecture/type": "lecture",
                    "https://class.whalespace.io/classes/class/chapters/chapter/lectures/lecture/tag-subject": "\uacbd\uc81c\ud559",
                    "https://class.whalespace.io/classes/class/chapters/chapter/lectures/lecture/tag": "\ub9c9\ud559\uae30",
                    "https://class.whalespace.io/classes/class/chapters/chapter/lectures/lecture/period-set/startdate": "2023-09-15T00:00:00Z",
                    "https://class.whalespace.io/classes/class/chapters/chapter/lectures/lecture/period-set/enddate": "2023-12-31T00:00:00Z"
                }
            }
        },
        "context": {
            "instructor": {
                "objectType": "Group",
                "account": {
                    "homePage": "https://class.whalespace.io/userInfo/base-info/555",
                    "name": "\ud559\uad501"
                },
                "member": [
                    {
                        "mbox": "mailto:999@class.whalespace.io",
                        "name": "\uc6e8\uc77c\ud074\ub798\uc2a4 \uad50\uc218\uc7901"
                    },
                    {
                        "mbox": "mailto:998@class.whalespace.io",
                        "name": "\uc6e8\uc77c\ud074\ub798\uc2a4 \uad50\uc218\uc7902"
                    }
                ]
            },
            "team": {
                "objectType": "Group",
                "account": {
                    "homePage": "https://class.whalespace.io/userInfo/base-info/333",
                    "name": "\uc18c\uc18d \uae30\uad00"
                }
            },
            "registration": "cf3ca788-d7cc-464e-a654-a98a777d2372",
            "revision": "1.0",
            "platform": "\uad50\uc721\uccad\ubcc4 \uc6e8\uc77c\ud074\ub798\uc2a4 \uc8fc\uc18c",
            "contextActivities": {
                "parent": [
                    {
                        "objectType": "Activity",
                        "id": "https://class.whalespace.io/data2/lectures/455106",
                        "definition": {
                            "type": "http://activitystrea.ms/schema/1.0/read",
                            "name": {
                                "en-US": "\ud074\ub798\uc2a4\uba85"
                            },
                            "description": {
                                "en-US": "null"
                            }
                        }
                    }
                ],
                "category": [
                    {
                        "objectType": "Activity",
                        "id": "http://class.whalespace.io/xapi/profile/lecture"
                    }
                ]
            },
            "extensions": {}
        }
    },
    {
        "object": {
            "id": "https://class.whalespace.io/bubblecon-guide/lecture/1019/contents/10191651",
            "objectType": "Activity",
            "definition": {
                "name": {
                    "en-US": "Guide to Astrophotography"
                },
                "description": {
                    "en-US": "Capturing stunning photos of celestial objects."
                },
                "type": "http://activitystrea.ms/schema/1.0/collection",
                "extensions": {
                    "https://class.whalespace.io/classes/class/chapters/chapter/lectures/lecture/content-id": 10191651,
                    "https://class.whalespace.io/classes/class/chapters/chapter/lectures/lecture/content-order": 2,
                    "https://class.whalespace.io/classes/class/id": 123,
                    "https://class.whalespace.io/classes/class/name": "\ud589\ubcf5\ud55c \ud074\ub798\uc2a4",
                    "https://class.whalespace.io/classes/class/type": "group",
                    "https://class.whalespace.io/classes/class/chapters/chapter/id": 123,
                    "https://class.whalespace.io/classes/class/chapters/chapter/name": "\ucc55\ud130 1",
                    "https://class.whalespace.io/classes/class/chapters/chapter/lectures/lecture/id": 1019,
                    "https://class.whalespace.io/classes/class/chapters/chapter/lectures/lecture/name": "\uacbd\uc81c\ud559 \uc785\ubb38",
                    "https://class.whalespace.io/classes/class/chapters/chapter/lectures/lecture/type": "lecture",
                    "https://class.whalespace.io/classes/class/chapters/chapter/lectures/lecture/tag-subject": "\uacbd\uc81c\ud559",
                    "https://class.whalespace.io/classes/class/chapters/chapter/lectures/lecture/tag": "\ub9c9\ud559\uae30",
                    "https://class.whalespace.io/classes/class/chapters/chapter/lectures/lecture/period-set/startdate": "2023-09-15T00:00:00Z",
                    "https://class.whalespace.io/classes/class/chapters/chapter/lectures/lecture/period-set/enddate": "2023-12-31T00:00:00Z"
                }
            }
        },
        "context": {
            "instructor": {
                "objectType": "Group",
                "account": {
                    "homePage": "https://class.whalespace.io/userInfo/base-info/555",
                    "name": "\ud559\uad501"
                },
                "member": [
                    {
                        "mbox": "mailto:999@class.whalespace.io",
                        "name": "\uc6e8\uc77c\ud074\ub798\uc2a4 \uad50\uc218\uc7901"
                    },
                    {
                        "mbox": "mailto:998@class.whalespace.io",
                        "name": "\uc6e8\uc77c\ud074\ub798\uc2a4 \uad50\uc218\uc7902"
                    }
                ]
            },
            "team": {
                "objectType": "Group",
                "account": {
                    "homePage": "https://class.whalespace.io/userInfo/base-info/333",
                    "name": "\uc18c\uc18d \uae30\uad00"
                }
            },
            "registration": "cf3ca788-d7cc-464e-a654-a98a777d2372",
            "revision": "1.0",
            "platform": "\uad50\uc721\uccad\ubcc4 \uc6e8\uc77c\ud074\ub798\uc2a4 \uc8fc\uc18c",
            "contextActivities": {
                "parent": [
                    {
                        "objectType": "Activity",
                        "id": "https://class.whalespace.io/data2/lectures/455106",
                        "definition": {
                            "type": "http://activitystrea.ms/schema/1.0/read",
                            "name": {
                                "en-US": "\ud074\ub798\uc2a4\uba85"
                            },
                            "description": {
                                "en-US": "null"
                            }
                        }
                    }
                ],
                "category": [
                    {
                        "objectType": "Activity",
                        "id": "http://class.whalespace.io/xapi/profile/lecture"
                    }
                ]
            },
            "extensions": {}
        }
    },
    {
        "object": {
            "id": "https://class.whalespace.io/bubblecon-guide/lecture/1019/contents/10191790",
            "objectType": "Activity",
            "definition": {
                "name": {
                    "en-US": "\ub77c\uc774\ube0c \uc9c8\uc758\uc751\ub2f5 \uc138\uc158: \uc6b0\uc8fc \ud0d0\uc0ac"
                },
                "description": {
                    "en-US": "\ucd5c\uadfc \uc6b0\uc8fc \ud0d0\uc0ac \uac1c\ubc1c\uc5d0 \ub300\ud574 \ub17c\uc758\ud558\ub294 \uc778\ud130\ub799\ud2f0\ube0c \uc138\uc158\uc785\ub2c8\ub2e4."
                },
                "type": "http://activitystrea.ms/schema/1.0/collection",
                "extensions": {
                    "https://class.whalespace.io/classes/class/chapters/chapter/lectures/lecture/content-id": 10191790,
                    "https://class.whalespace.io/classes/class/chapters/chapter/lectures/lecture/content-order": 3,
                    "https://class.whalespace.io/classes/class/id": 123,
                    "https://class.whalespace.io/classes/class/name": "\ud589\ubcf5\ud55c \ud074\ub798\uc2a4",
                    "https://class.whalespace.io/classes/class/type": "group",
                    "https://class.whalespace.io/classes/class/chapters/chapter/id": 123,
                    "https://class.whalespace.io/classes/class/chapters/chapter/name": "\ucc55\ud130 1",
                    "https://class.whalespace.io/classes/class/chapters/chapter/lectures/lecture/id": 1019,
                    "https://class.whalespace.io/classes/class/chapters/chapter/lectures/lecture/name": "\uacbd\uc81c\ud559 \uc785\ubb38",
                    "https://class.whalespace.io/classes/class/chapters/chapter/lectures/lecture/type": "lecture",
                    "https://class.whalespace.io/classes/class/chapters/chapter/lectures/lecture/tag-subject": "\uacbd\uc81c\ud559",
                    "https://class.whalespace.io/classes/class/chapters/chapter/lectures/lecture/tag": "\ub9c9\ud559\uae30",
                    "https://class.whalespace.io/classes/class/chapters/chapter/lectures/lecture/period-set/startdate": "2023-09-15T00:00:00Z",
                    "https://class.whalespace.io/classes/class/chapters/chapter/lectures/lecture/period-set/enddate": "2023-12-31T00:00:00Z"
                }
            }
        },
        "context": {
            "instructor": {
                "objectType": "Group",
                "account": {
                    "homePage": "https://class.whalespace.io/userInfo/base-info/555",
                    "name": "\ud559\uad501"
                },
                "member": [
                    {
                        "mbox": "mailto:999@class.whalespace.io",
                        "name": "\uc6e8\uc77c\ud074\ub798\uc2a4 \uad50\uc218\uc7901"
                    },
                    {
                        "mbox": "mailto:998@class.whalespace.io",
                        "name": "\uc6e8\uc77c\ud074\ub798\uc2a4 \uad50\uc218\uc7902"
                    }
                ]
            },
            "team": {
                "objectType": "Group",
                "account": {
                    "homePage": "https://class.whalespace.io/userInfo/base-info/333",
                    "name": "\uc18c\uc18d \uae30\uad00"
                }
            },
            "registration": "cf3ca788-d7cc-464e-a654-a98a777d2372",
            "revision": "1.0",
            "platform": "\uad50\uc721\uccad\ubcc4 \uc6e8\uc77c\ud074\ub798\uc2a4 \uc8fc\uc18c",
            "contextActivities": {
                "parent": [
                    {
                        "objectType": "Activity",
                        "id": "https://class.whalespace.io/data2/lectures/455106",
                        "definition": {
                            "type": "http://activitystrea.ms/schema/1.0/read",
                            "name": {
                                "en-US": "\ud074\ub798\uc2a4\uba85"
                            },
                            "description": {
                                "en-US": "null"
                            }
                        }
                    }
                ],
                "category": [
                    {
                        "objectType": "Activity",
                        "id": "http://class.whalespace.io/xapi/profile/lecture"
                    }
                ]
            },
            "extensions": {}
        }
    },
    {
        "object": {
            "id": "https://class.whalespace.io/bubblecon-guide/lecture/1019/contents/10191939",
            "objectType": "Activity",
            "definition": {
                "name": {
                    "en-US": "\uac1d\uccb4 \uc9c0\ud5a5 \ud504\ub85c\uadf8\ub798\ubc0d \uc6d0\ub9ac"
                },
                "description": {
                    "en-US": "\uac1d\uccb4 \uc9c0\ud5a5 \ud504\ub85c\uadf8\ub798\ubc0d\uc758 \uae30\ubcf8 \uc6d0\ub9ac\ub97c \ud0d0\uad6c\ud569\ub2c8\ub2e4."
                },
                "type": "http://activitystrea.ms/schema/1.0/collection",
                "extensions": {
                    "https://class.whalespace.io/classes/class/chapters/chapter/lectures/lecture/content-id": 10191939,
                    "https://class.whalespace.io/classes/class/chapters/chapter/lectures/lecture/content-order": 4,
                    "https://class.whalespace.io/classes/class/id": 123,
                    "https://class.whalespace.io/classes/class/name": "\ud589\ubcf5\ud55c \ud074\ub798\uc2a4",
                    "https://class.whalespace.io/classes/class/type": "group",
                    "https://class.whalespace.io/classes/class/chapters/chapter/id": 123,
                    "https://class.whalespace.io/classes/class/chapters/chapter/name": "\ucc55\ud130 1",
                    "https://class.whalespace.io/classes/class/chapters/chapter/lectures/lecture/id": 1019,
                    "https://class.whalespace.io/classes/class/chapters/chapter/lectures/lecture/name": "\uacbd\uc81c\ud559 \uc785\ubb38",
                    "https://class.whalespace.io/classes/class/chapters/chapter/lectures/lecture/type": "lecture",
                    "https://class.whalespace.io/classes/class/chapters/chapter/lectures/lecture/tag-subject": "\uacbd\uc81c\ud559",
                    "https://class.whalespace.io/classes/class/chapters/chapter/lectures/lecture/tag": "\ub9c9\ud559\uae30",
                    "https://class.whalespace.io/classes/class/chapters/chapter/lectures/lecture/period-set/startdate": "2023-09-15T00:00:00Z",
                    "https://class.whalespace.io/classes/class/chapters/chapter/lectures/lecture/period-set/enddate": "2023-12-31T00:00:00Z"
                }
            }
        },
        "context": {
            "instructor": {
                "objectType": "Group",
                "account": {
                    "homePage": "https://class.whalespace.io/userInfo/base-info/555",
                    "name": "\ud559\uad501"
                },
                "member": [
                    {
                        "mbox": "mailto:999@class.whalespace.io",
                        "name": "\uc6e8\uc77c\ud074\ub798\uc2a4 \uad50\uc218\uc7901"
                    },
                    {
                        "mbox": "mailto:998@class.whalespace.io",
                        "name": "\uc6e8\uc77c\ud074\ub798\uc2a4 \uad50\uc218\uc7902"
                    }
                ]
            },
            "team": {
                "objectType": "Group",
                "account": {
                    "homePage": "https://class.whalespace.io/userInfo/base-info/333",
                    "name": "\uc18c\uc18d \uae30\uad00"
                }
            },
            "registration": "cf3ca788-d7cc-464e-a654-a98a777d2372",
            "revision": "1.0",
            "platform": "\uad50\uc721\uccad\ubcc4 \uc6e8\uc77c\ud074\ub798\uc2a4 \uc8fc\uc18c",
            "contextActivities": {
                "parent": [
                    {
                        "objectType": "Activity",
                        "id": "https://class.whalespace.io/data2/lectures/455106",
                        "definition": {
                            "type": "http://activitystrea.ms/schema/1.0/read",
                            "name": {
                                "en-US": "\ud074\ub798\uc2a4\uba85"
                            },
                            "description": {
                                "en-US": "null"
                            }
                        }
                    }
                ],
                "category": [
                    {
                        "objectType": "Activity",
                        "id": "http://class.whalespace.io/xapi/profile/lecture"
                    }
                ]
            },
            "extensions": {}
        }
    },
    {
        "object": {
            "id": "https://class.whalespace.io/bubblecon-guide/lecture/1019/contents/10192104",
            "objectType": "Activity",
            "definition": {
                "name": {
                    "en-US": "\uae30\ud6c4 \ubcc0\ud654 \uc0ac\uc2e4\uacfc \ud574\uacb0\ucc45"
                },
                "description": {
                    "en-US": "\uae30\ud6c4 \ubcc0\ud654\ub97c \uc774\ud574\ud558\uace0 \ub300\uc751 \ubc29\ubc95\uc744 \ubc30\uc6c1\ub2c8\ub2e4."
                },
                "type": "http://activitystrea.ms/schema/1.0/collection",
                "extensions": {
                    "https://class.whalespace.io/classes/class/chapters/chapter/lectures/lecture/content-id": 10192104,
                    "https://class.whalespace.io/classes/class/chapters/chapter/lectures/lecture/content-order": 5,
                    "https://class.whalespace.io/classes/class/id": 123,
                    "https://class.whalespace.io/classes/class/name": "\ud589\ubcf5\ud55c \ud074\ub798\uc2a4",
                    "https://class.whalespace.io/classes/class/type": "group",
                    "https://class.whalespace.io/classes/class/chapters/chapter/id": 123,
                    "https://class.whalespace.io/classes/class/chapters/chapter/name": "\ucc55\ud130 1",
                    "https://class.whalespace.io/classes/class/chapters/chapter/lectures/lecture/id": 1019,
                    "https://class.whalespace.io/classes/class/chapters/chapter/lectures/lecture/name": "\uacbd\uc81c\ud559 \uc785\ubb38",
                    "https://class.whalespace.io/classes/class/chapters/chapter/lectures/lecture/type": "lecture",
                    "https://class.whalespace.io/classes/class/chapters/chapter/lectures/lecture/tag-subject": "\uacbd\uc81c\ud559",
                    "https://class.whalespace.io/classes/class/chapters/chapter/lectures/lecture/tag": "\ub9c9\ud559\uae30",
                    "https://class.whalespace.io/classes/class/chapters/chapter/lectures/lecture/period-set/startdate": "2023-09-15T00:00:00Z",
                    "https://class.whalespace.io/classes/class/chapters/chapter/lectures/lecture/period-set/enddate": "2023-12-31T00:00:00Z"
                }
            }
        },
        "context": {
            "instructor": {
                "objectType": "Group",
                "account": {
                    "homePage": "https://class.whalespace.io/userInfo/base-info/555",
                    "name": "\ud559\uad501"
                },
                "member": [
                    {
                        "mbox": "mailto:999@class.whalespace.io",
                        "name": "\uc6e8\uc77c\ud074\ub798\uc2a4 \uad50\uc218\uc7901"
                    },
                    {
                        "mbox": "mailto:998@class.whalespace.io",
                        "name": "\uc6e8\uc77c\ud074\ub798\uc2a4 \uad50\uc218\uc7902"
                    }
                ]
            },
            "team": {
                "objectType": "Group",
                "account": {
                    "homePage": "https://class.whalespace.io/userInfo/base-info/333",
                    "name": "\uc18c\uc18d \uae30\uad00"
                }
            },
            "registration": "cf3ca788-d7cc-464e-a654-a98a777d2372",
            "revision": "1.0",
            "platform": "\uad50\uc721\uccad\ubcc4 \uc6e8\uc77c\ud074\ub798\uc2a4 \uc8fc\uc18c",
            "contextActivities": {
                "parent": [
                    {
                        "objectType": "Activity",
                        "id": "https://class.whalespace.io/data2/lectures/455106",
                        "definition": {
                            "type": "http://activitystrea.ms/schema/1.0/read",
                            "name": {
                                "en-US": "\ud074\ub798\uc2a4\uba85"
                            },
                            "description": {
                                "en-US": "null"
                            }
                        }
                    }
                ],
                "category": [
                    {
                        "objectType": "Activity",
                        "id": "http://class.whalespace.io/xapi/profile/lecture"
                    }
                ]
            },
            "extensions": {}
        }
    },
    {
        "object": {
            "id": "https://class.whalespace.io/bubblecon-guide/lecture/1019/contents/1019483",
            "objectType": "Activity",
            "definition": {
                "name": {
                    "en-US": "\uc6d0\uc608 \ucd08\ubcf4\uc790\ub97c \uc704\ud55c \uc548\ub0b4\uc11c"
                },
                "description": {
                    "en-US": "\uc815\uc6d0 \uac00\uafb8\uae30\uc640 \uc2dd\ubb3c \uad00\ub9ac\uc5d0 \ub300\ud55c \ud301\uc785\ub2c8\ub2e4."
                },
                "type": "http://activitystrea.ms/schema/1.0/collection",
                "extensions": {
                    "https://class.whalespace.io/classes/class/chapters/chapter/lectures/lecture/content-id": 1019483,
                    "https://class.whalespace.io/classes/class/chapters/chapter/lectures/lecture/content-order": 6,
                    "https://class.whalespace.io/classes/class/id": 123,
                    "https://class.whalespace.io/classes/class/name": "\ud589\ubcf5\ud55c \ud074\ub798\uc2a4",
                    "https://class.whalespace.io/classes/class/type": "group",
                    "https://class.whalespace.io/classes/class/chapters/chapter/id": 123,
                    "https://class.whalespace.io/classes/class/chapters/chapter/name": "\ucc55\ud130 1",
                    "https://class.whalespace.io/classes/class/chapters/chapter/lectures/lecture/id": 1019,
                    "https://class.whalespace.io/classes/class/chapters/chapter/lectures/lecture/name": "\uacbd\uc81c\ud559 \uc785\ubb38",
                    "https://class.whalespace.io/classes/class/chapters/chapter/lectures/lecture/type": "lecture",
                    "https://class.whalespace.io/classes/class/chapters/chapter/lectures/lecture/tag-subject": "\uacbd\uc81c\ud559",
                    "https://class.whalespace.io/classes/class/chapters/chapter/lectures/lecture/tag": "\ub9c9\ud559\uae30",
                    "https://class.whalespace.io/classes/class/chapters/chapter/lectures/lecture/period-set/startdate": "2023-09-15T00:00:00Z",
                    "https://class.whalespace.io/classes/class/chapters/chapter/lectures/lecture/period-set/enddate": "2023-12-31T00:00:00Z"
                }
            }
        },
        "context": {
            "instructor": {
                "objectType": "Group",
                "account": {
                    "homePage": "https://class.whalespace.io/userInfo/base-info/555",
                    "name": "\ud559\uad501"
                },
                "member": [
                    {
                        "mbox": "mailto:999@class.whalespace.io",
                        "name": "\uc6e8\uc77c\ud074\ub798\uc2a4 \uad50\uc218\uc7901"
                    },
                    {
                        "mbox": "mailto:998@class.whalespace.io",
                        "name": "\uc6e8\uc77c\ud074\ub798\uc2a4 \uad50\uc218\uc7902"
                    }
                ]
            },
            "team": {
                "objectType": "Group",
                "account": {
                    "homePage": "https://class.whalespace.io/userInfo/base-info/333",
                    "name": "\uc18c\uc18d \uae30\uad00"
                }
            },
            "registration": "cf3ca788-d7cc-464e-a654-a98a777d2372",
            "revision": "1.0",
            "platform": "\uad50\uc721\uccad\ubcc4 \uc6e8\uc77c\ud074\ub798\uc2a4 \uc8fc\uc18c",
            "contextActivities": {
                "parent": [
                    {
                        "objectType": "Activity",
                        "id": "https://class.whalespace.io/data2/lectures/455106",
                        "definition": {
                            "type": "http://activitystrea.ms/schema/1.0/read",
                            "name": {
                                "en-US": "\ud074\ub798\uc2a4\uba85"
                            },
                            "description": {
                                "en-US": "null"
                            }
                        }
                    }
                ],
                "category": [
                    {
                        "objectType": "Activity",
                        "id": "http://class.whalespace.io/xapi/profile/lecture"
                    }
                ]
            },
            "extensions": {}
        }
    },
    {
        "object": {
            "id": "https://class.whalespace.io/bubblecon-guide/lecture/1019/contents/1019774",
            "objectType": "Activity",
            "definition": {
                "name": {
                    "en-US": "Data Structures and Algorithms"
                },
                "description": {
                    "en-US": "Understanding common data structures and algorithms."
                },
                "type": "http://activitystrea.ms/schema/1.0/collection",
                "extensions": {
                    "https://class.whalespace.io/classes/class/chapters/chapter/lectures/lecture/content-id": 1019774,
                    "https://class.whalespace.io/classes/class/chapters/chapter/lectures/lecture/content-order": 7,
                    "https://class.whalespace.io/classes/class/id": 123,
                    "https://class.whalespace.io/classes/class/name": "\ud589\ubcf5\ud55c \ud074\ub798\uc2a4",
                    "https://class.whalespace.io/classes/class/type": "group",
                    "https://class.whalespace.io/classes/class/chapters/chapter/id": 123,
                    "https://class.whalespace.io/classes/class/chapters/chapter/name": "\ucc55\ud130 1",
                    "https://class.whalespace.io/classes/class/chapters/chapter/lectures/lecture/id": 1019,
                    "https://class.whalespace.io/classes/class/chapters/chapter/lectures/lecture/name": "\uacbd\uc81c\ud559 \uc785\ubb38",
                    "https://class.whalespace.io/classes/class/chapters/chapter/lectures/lecture/type": "lecture",
                    "https://class.whalespace.io/classes/class/chapters/chapter/lectures/lecture/tag-subject": "\uacbd\uc81c\ud559",
                    "https://class.whalespace.io/classes/class/chapters/chapter/lectures/lecture/tag": "\ub9c9\ud559\uae30",
                    "https://class.whalespace.io/classes/class/chapters/chapter/lectures/lecture/period-set/startdate": "2023-09-15T00:00:00Z",
                    "https://class.whalespace.io/classes/class/chapters/chapter/lectures/lecture/period-set/enddate": "2023-12-31T00:00:00Z"
                }
            }
        },
        "context": {
            "instructor": {
                "objectType": "Group",
                "account": {
                    "homePage": "https://class.whalespace.io/userInfo/base-info/555",
                    "name": "\ud559\uad501"
                },
                "member": [
                    {
                        "mbox": "mailto:999@class.whalespace.io",
                        "name": "\uc6e8\uc77c\ud074\ub798\uc2a4 \uad50\uc218\uc7901"
                    },
                    {
                        "mbox": "mailto:998@class.whalespace.io",
                        "name": "\uc6e8\uc77c\ud074\ub798\uc2a4 \uad50\uc218\uc7902"
                    }
                ]
            },
            "team": {
                "objectType": "Group",
                "account": {
                    "homePage": "https://class.whalespace.io/userInfo/base-info/333",
                    "name": "\uc18c\uc18d \uae30\uad00"
                }
            },
            "registration": "cf3ca788-d7cc-464e-a654-a98a777d2372",
            "revision": "1.0",
            "platform": "\uad50\uc721\uccad\ubcc4 \uc6e8\uc77c\ud074\ub798\uc2a4 \uc8fc\uc18c",
            "contextActivities": {
                "parent": [
                    {
                        "objectType": "Activity",
                        "id": "https://class.whalespace.io/data2/lectures/455106",
                        "definition": {
                            "type": "http://activitystrea.ms/schema/1.0/read",
                            "name": {
                                "en-US": "\ud074\ub798\uc2a4\uba85"
                            },
                            "description": {
                                "en-US": "null"
                            }
                        }
                    }
                ],
                "category": [
                    {
                        "objectType": "Activity",
                        "id": "http://class.whalespace.io/xapi/profile/lecture"
                    }
                ]
            },
            "extensions": {}
        }
    },
    {
        "object": {
            "id": "https://class.whalespace.io/bubblecon-guide/lecture/1019/contents/1019143",
            "objectType": "Activity",
            "definition": {
                "name": {
                    "en-US": "Climate Change Facts and Solutions"
                },
                "description": {
                    "en-US": "Understanding climate change and ways to address it."
                },
                "type": "http://activitystrea.ms/schema/1.0/collection",
                "extensions": {
                    "https://class.whalespace.io/classes/class/chapters/chapter/lectures/lecture/content-id": 1019143,
                    "https://class.whalespace.io/classes/class/chapters/chapter/lectures/lecture/content-order": 8,
                    "https://class.whalespace.io/classes/class/id": 123,
                    "https://class.whalespace.io/classes/class/name": "\ud589\ubcf5\ud55c \ud074\ub798\uc2a4",
                    "https://class.whalespace.io/classes/class/type": "group",
                    "https://class.whalespace.io/classes/class/chapters/chapter/id": 123,
                    "https://class.whalespace.io/classes/class/chapters/chapter/name": "\ucc55\ud130 1",
                    "https://class.whalespace.io/classes/class/chapters/chapter/lectures/lecture/id": 1019,
                    "https://class.whalespace.io/classes/class/chapters/chapter/lectures/lecture/name": "\uacbd\uc81c\ud559 \uc785\ubb38",
                    "https://class.whalespace.io/classes/class/chapters/chapter/lectures/lecture/type": "lecture",
                    "https://class.whalespace.io/classes/class/chapters/chapter/lectures/lecture/tag-subject": "\uacbd\uc81c\ud559",
                    "https://class.whalespace.io/classes/class/chapters/chapter/lectures/lecture/tag": "\ub9c9\ud559\uae30",
                    "https://class.whalespace.io/classes/class/chapters/chapter/lectures/lecture/period-set/startdate": "2023-09-15T00:00:00Z",
                    "https://class.whalespace.io/classes/class/chapters/chapter/lectures/lecture/period-set/enddate": "2023-12-31T00:00:00Z"
                }
            }
        },
        "context": {
            "instructor": {
                "objectType": "Group",
                "account": {
                    "homePage": "https://class.whalespace.io/userInfo/base-info/555",
                    "name": "\ud559\uad501"
                },
                "member": [
                    {
                        "mbox": "mailto:999@class.whalespace.io",
                        "name": "\uc6e8\uc77c\ud074\ub798\uc2a4 \uad50\uc218\uc7901"
                    },
                    {
                        "mbox": "mailto:998@class.whalespace.io",
                        "name": "\uc6e8\uc77c\ud074\ub798\uc2a4 \uad50\uc218\uc7902"
                    }
                ]
            },
            "team": {
                "objectType": "Group",
                "account": {
                    "homePage": "https://class.whalespace.io/userInfo/base-info/333",
                    "name": "\uc18c\uc18d \uae30\uad00"
                }
            },
            "registration": "cf3ca788-d7cc-464e-a654-a98a777d2372",
            "revision": "1.0",
            "platform": "\uad50\uc721\uccad\ubcc4 \uc6e8\uc77c\ud074\ub798\uc2a4 \uc8fc\uc18c",
            "contextActivities": {
                "parent": [
                    {
                        "objectType": "Activity",
                        "id": "https://class.whalespace.io/data2/lectures/455106",
                        "definition": {
                            "type": "http://activitystrea.ms/schema/1.0/read",
                            "name": {
                                "en-US": "\ud074\ub798\uc2a4\uba85"
                            },
                            "description": {
                                "en-US": "null"
                            }
                        }
                    }
                ],
                "category": [
                    {
                        "objectType": "Activity",
                        "id": "http://class.whalespace.io/xapi/profile/lecture"
                    }
                ]
            },
            "extensions": {}
        }
    },
    {
        "object": {
            "id": "https://class.whalespace.io/bubblecon-guide/lecture/1019/contents/1019502",
            "objectType": "Activity",
            "definition": {
                "name": {
                    "en-US": "\uc6f9 \uac1c\ubc1c \uae30\ucd08"
                },
                "description": {
                    "en-US": "HTML, CSS \ubc0f JavaScript \uc18c\uac1c\uc785\ub2c8\ub2e4."
                },
                "type": "http://activitystrea.ms/schema/1.0/collection",
                "extensions": {
                    "https://class.whalespace.io/classes/class/chapters/chapter/lectures/lecture/content-id": 1019502,
                    "https://class.whalespace.io/classes/class/chapters/chapter/lectures/lecture/content-order": 9,
                    "https://class.whalespace.io/classes/class/id": 123,
                    "https://class.whalespace.io/classes/class/name": "\ud589\ubcf5\ud55c \ud074\ub798\uc2a4",
                    "https://class.whalespace.io/classes/class/type": "group",
                    "https://class.whalespace.io/classes/class/chapters/chapter/id": 123,
                    "https://class.whalespace.io/classes/class/chapters/chapter/name": "\ucc55\ud130 1",
                    "https://class.whalespace.io/classes/class/chapters/chapter/lectures/lecture/id": 1019,
                    "https://class.whalespace.io/classes/class/chapters/chapter/lectures/lecture/name": "\uacbd\uc81c\ud559 \uc785\ubb38",
                    "https://class.whalespace.io/classes/class/chapters/chapter/lectures/lecture/type": "lecture",
                    "https://class.whalespace.io/classes/class/chapters/chapter/lectures/lecture/tag-subject": "\uacbd\uc81c\ud559",
                    "https://class.whalespace.io/classes/class/chapters/chapter/lectures/lecture/tag": "\ub9c9\ud559\uae30",
                    "https://class.whalespace.io/classes/class/chapters/chapter/lectures/lecture/period-set/startdate": "2023-09-15T00:00:00Z",
                    "https://class.whalespace.io/classes/class/chapters/chapter/lectures/lecture/period-set/enddate": "2023-12-31T00:00:00Z"
                }
            }
        },
        "context": {
            "instructor": {
                "objectType": "Group",
                "account": {
                    "homePage": "https://class.whalespace.io/userInfo/base-info/555",
                    "name": "\ud559\uad501"
                },
                "member": [
                    {
                        "mbox": "mailto:999@class.whalespace.io",
                        "name": "\uc6e8\uc77c\ud074\ub798\uc2a4 \uad50\uc218\uc7901"
                    },
                    {
                        "mbox": "mailto:998@class.whalespace.io",
                        "name": "\uc6e8\uc77c\ud074\ub798\uc2a4 \uad50\uc218\uc7902"
                    }
                ]
            },
            "team": {
                "objectType": "Group",
                "account": {
                    "homePage": "https://class.whalespace.io/userInfo/base-info/333",
                    "name": "\uc18c\uc18d \uae30\uad00"
                }
            },
            "registration": "cf3ca788-d7cc-464e-a654-a98a777d2372",
            "revision": "1.0",
            "platform": "\uad50\uc721\uccad\ubcc4 \uc6e8\uc77c\ud074\ub798\uc2a4 \uc8fc\uc18c",
            "contextActivities": {
                "parent": [
                    {
                        "objectType": "Activity",
                        "id": "https://class.whalespace.io/data2/lectures/455106",
                        "definition": {
                            "type": "http://activitystrea.ms/schema/1.0/read",
                            "name": {
                                "en-US": "\ud074\ub798\uc2a4\uba85"
                            },
                            "description": {
                                "en-US": "null"
                            }
                        }
                    }
                ],
                "category": [
                    {
                        "objectType": "Activity",
                        "id": "http://class.whalespace.io/xapi/profile/lecture"
                    }
                ]
            },
            "extensions": {}
        }
    },
    {
        "object": {
            "id": "https://class.whalespace.io/bubblecon-guide/lecture/1019/contents/1019525",
            "objectType": "Activity",
            "definition": {
                "name": {
                    "en-US": "Video Editing Techniques"
                },
                "description": {
                    "en-US": "Learn various video editing techniques."
                },
                "type": "http://activitystrea.ms/schema/1.0/collection",
                "extensions": {
                    "https://class.whalespace.io/classes/class/chapters/chapter/lectures/lecture/content-id": 1019525,
                    "https://class.whalespace.io/classes/class/chapters/chapter/lectures/lecture/content-order": 10,
                    "https://class.whalespace.io/classes/class/id": 123,
                    "https://class.whalespace.io/classes/class/name": "\ud589\ubcf5\ud55c \ud074\ub798\uc2a4",
                    "https://class.whalespace.io/classes/class/type": "group",
                    "https://class.whalespace.io/classes/class/chapters/chapter/id": 123,
                    "https://class.whalespace.io/classes/class/chapters/chapter/name": "\ucc55\ud130 1",
                    "https://class.whalespace.io/classes/class/chapters/chapter/lectures/lecture/id": 1019,
                    "https://class.whalespace.io/classes/class/chapters/chapter/lectures/lecture/name": "\uacbd\uc81c\ud559 \uc785\ubb38",
                    "https://class.whalespace.io/classes/class/chapters/chapter/lectures/lecture/type": "lecture",
                    "https://class.whalespace.io/classes/class/chapters/chapter/lectures/lecture/tag-subject": "\uacbd\uc81c\ud559",
                    "https://class.whalespace.io/classes/class/chapters/chapter/lectures/lecture/tag": "\ub9c9\ud559\uae30",
                    "https://class.whalespace.io/classes/class/chapters/chapter/lectures/lecture/period-set/startdate": "2023-09-15T00:00:00Z",
                    "https://class.whalespace.io/classes/class/chapters/chapter/lectures/lecture/period-set/enddate": "2023-12-31T00:00:00Z"
                }
            }
        },
        "context": {
            "instructor": {
                "objectType": "Group",
                "account": {
                    "homePage": "https://class.whalespace.io/userInfo/base-info/555",
                    "name": "\ud559\uad501"
                },
                "member": [
                    {
                        "mbox": "mailto:999@class.whalespace.io",
                        "name": "\uc6e8\uc77c\ud074\ub798\uc2a4 \uad50\uc218\uc7901"
                    },
                    {
                        "mbox": "mailto:998@class.whalespace.io",
                        "name": "\uc6e8\uc77c\ud074\ub798\uc2a4 \uad50\uc218\uc7902"
                    }
                ]
            },
            "team": {
                "objectType": "Group",
                "account": {
                    "homePage": "https://class.whalespace.io/userInfo/base-info/333",
                    "name": "\uc18c\uc18d \uae30\uad00"
                }
            },
            "registration": "cf3ca788-d7cc-464e-a654-a98a777d2372",
            "revision": "1.0",
            "platform": "\uad50\uc721\uccad\ubcc4 \uc6e8\uc77c\ud074\ub798\uc2a4 \uc8fc\uc18c",
            "contextActivities": {
                "parent": [
                    {
                        "objectType": "Activity",
                        "id": "https://class.whalespace.io/data2/lectures/455106",
                        "definition": {
                            "type": "http://activitystrea.ms/schema/1.0/read",
                            "name": {
                                "en-US": "\ud074\ub798\uc2a4\uba85"
                            },
                            "description": {
                                "en-US": "null"
                            }
                        }
                    }
                ],
                "category": [
                    {
                        "objectType": "Activity",
                        "id": "http://class.whalespace.io/xapi/profile/lecture"
                    }
                ]
            },
            "extensions": {}
        }
    }
]